schematix/__init__.py
schematix/core/__init__.py
schematix/core/deps.py
schematix/core/field.py
schematix/core/schema.py
schematix/core/transform.py
schematix/core/bases/__init__.py
schematix/core/bases/field.py
schematix/core/bases/schema.py
schematix/core/bases/transform.py
schematix/core/metas/__init__.py
schematix/core/metas/field.py
schematix/core/metas/schema.py
schematix/decorators/__init__.py
schematix/decorators/field.py
schematix/decorators/schema.py
schematix/transforms/__init__.py
schematix/transforms/collections.py
schematix/transforms/common.py
schematix/transforms/dates.py
schematix/transforms/numbers.py
schematix/transforms/text.py
schematix/transforms/validation.py
schematix-0.4.71.dist-info/METADATA
schematix-0.4.71.dist-info/WHEEL
schematix-0.4.71.dist-info/RECORD
